database_automation_mongo/__init__.py
database_automation_mongo/mongo_crud.py
database_automation_mongo-0.0.4.dist-info/LICENSE
database_automation_mongo-0.0.4.dist-info/METADATA
database_automation_mongo-0.0.4.dist-info/WHEEL
database_automation_mongo-0.0.4.dist-info/top_level.txt
database_automation_mongo-0.0.4.dist-info/RECORD
