Metadata-Version: 2.1
Name: database_automation_mongo
Version: 0.0.4
Summary: A python package for connecting with database.
Home-page: https://github.com/Sankalpa0011/MongoDB-Connector-PYPI-Package
Author: Sankalpa0011
Author-email: sankalpakavindu09@gmail.com
License: MIT
Project-URL: Bug Tracker, https://github.com/Sankalpa0011/MongoDB-Connector-PYPI-Package/issues
Classifier: Programming Language :: Python :: 3.7
Classifier: Programming Language :: Python :: 3.8
Classifier: Programming Language :: Python :: 3.9
Classifier: Operating System :: OS Independent
Requires-Python: >=3.7
License-File: LICENSE
Requires-Dist: pymongo
Requires-Dist: pymongo[srv]
Requires-Dist: dnspython
Requires-Dist: pandas
Requires-Dist: numpy
Requires-Dist: ensure
Requires-Dist: pytest==7.1.3
Requires-Dist: tox==3.28.0
Requires-Dist: tox-gh-actions==2.11.0
Requires-Dist: black==22.8.0
Requires-Dist: flake8==5.0.4
Requires-Dist: mypy==0.971
Provides-Extra: testing
Requires-Dist: pytest>=7.1.3; extra == "testing"
Requires-Dist: mypy>=0.971; extra == "testing"
Requires-Dist: flake8>=5.0.4; extra == "testing"
Requires-Dist: tox>=3.25.1; extra == "testing"
Requires-Dist: black>=22.8.0; extra == "testing"
